{
  "ok": true,
  "source": "snapshot",
  "tradeType": 1,
  "sectors": [
    {
      "updateTime": 1781713800000,
      "tradeType": 1,
      "tag": "bStocks",
      "tagsSimplified": "bStocks",
      "categoriesTradeDataList": [
        {
          "timeRange": "m5",
          "timeParticleEnum": 5,
          "tradeInflow": "58036.959177"
        },
        {
          "timeRange": "m15",
          "timeParticleEnum": 15,
          "tradeInflow": "-142642.31540700002"
        },
        {
          "timeRange": "m30",
          "timeParticleEnum": 30,
          "tradeInflow": "9709.477517999978"
        },
        {
          "timeRange": "H1",
          "timeParticleEnum": 101,
          "tradeInflow": "-356530.4281099999"
        },
        {
          "timeRange": "H2",
          "timeParticleEnum": 102,
          "tradeInflow": "1931166.0828899993"
        },
        {
          "timeRange": "H4",
          "timeParticleEnum": 104,
          "tradeInflow": "2975791.7953360016"
        },
        {
          "timeRange": "H8",
          "timeParticleEnum": 108,
          "tradeInflow": "2724731.530829001"
        },
        {
          "timeRange": "H12",
          "timeParticleEnum": 112,
          "tradeInflow": "3665449.6705390015"
        },
        {
          "timeRange": "H24",
          "timeParticleEnum": 124,
          "tradeInflow": "5297219.172450001"
        },
        {
          "timeRange": "D2",
          "timeParticleEnum": 202,
          "tradeInflow": "9443402.056291003"
        },
        {
          "timeRange": "D3",
          "timeParticleEnum": 203,
          "tradeInflow": "9572748.651037"
        },
        {
          "timeRange": "D5",
          "timeParticleEnum": 205,
          "tradeInflow": "7807544.451982001"
        }
      ]
    },
    {
      "updateTime": 1781713800000,
      "tradeType": 1,
      "tag": "Payments",
      "tagsSimplified": "Payments",
      "categoriesTradeDataList": [
        {
          "timeRange": "m5",
          "timeParticleEnum": 5,
          "tradeInflow": "6891908.457572501"
        },
        {
          "timeRange": "m15",
          "timeParticleEnum": 15,
          "tradeInflow": "6135113.95837082"
        },
        {
          "timeRange": "m30",
          "timeParticleEnum": 30,
          "tradeInflow": "-835109.7463771936"
        },
        {
          "timeRange": "H1",
          "timeParticleEnum": 101,
          "tradeInflow": "9142863.505379999"
        },
        {
          "timeRange": "H2",
          "timeParticleEnum": 102,
          "tradeInflow": "10044116.54675601"
        },
        {
          "timeRange": "H4",
          "timeParticleEnum": 104,
          "tradeInflow": "27276842.094581623"
        },
        {
          "timeRange": "H8",
          "timeParticleEnum": 108,
          "tradeInflow": "8056623.723923877"
        },
        {
          "timeRange": "H12",
          "timeParticleEnum": 112,
          "tradeInflow": "-41836359.170444556"
        },
        {
          "timeRange": "H24",
          "timeParticleEnum": 124,
          "tradeInflow": "-27087172.547771987"
        },
        {
          "timeRange": "D2",
          "timeParticleEnum": 202,
          "tradeInflow": "-124398378.37406656"
        },
        {
          "timeRange": "D3",
          "timeParticleEnum": 203,
          "tradeInflow": "-38427815.84086861"
        },
        {
          "timeRange": "D5",
          "timeParticleEnum": 205,
          "tradeInflow": "-22800748.617030784"
        },
        {
          "timeRange": "D7",
          "timeParticleEnum": 207,
          "tradeInflow": "48941686.27695612"
        },
        {
          "timeRange": "D10",
          "timeParticleEnum": 210,
          "tradeInflow": "2021035.7512582222"
        },
        {
          "timeRange": "D15",
          "timeParticleEnum": 215,
          "tradeInflow": "-781752184.867029"
        },
        {
          "timeRange": "D30",
          "timeParticleEnum": 230,
          "tradeInflow": "-1189245898.7389154"
        },
        {
          "timeRange": "D40",
          "timeParticleEnum": 240,
          "tradeInflow": "-1552757138.5793045"
        },
        {
          "timeRange": "D50",
          "timeParticleEnum": 250,
          "tradeInflow": "-1411871164.193893"
        },
        {
          "timeRange": "D60",
          "timeParticleEnum": 260,
          "tradeInflow": "-1568596860.6103785"
        },
        {
          "timeRange": "D90",
          "timeParticleEnum": 290,
          "tradeInflow": "-1496115481.3580346"
        },
        {
          "timeRange": "Y1",
          "timeParticleEnum": 401,
          "tradeInflow": "-27686565546.592377"
        },
        {
          "timeRange": "Y2",
          "timeParticleEnum": 402,
          "tradeInflow": "-49211781366.26632"
        },
        {
          "timeRange": "Y3",
          "timeParticleEnum": 403,
          "tradeInflow": "-55643155680.645966"
        },
        {
          "timeRange": "D120",
          "timeParticleEnum": 2120,
          "tradeInflow": "-2638177981.165137"
        },
        {
          "timeRange": "D150",
          "timeParticleEnum": 2150,
          "tradeInflow": "-7134419615.009455"
        },
        {
          "timeRange": "D180",
          "timeParticleEnum": 2180,
          "tradeInflow": "-7102840662.214703"
        }
      ]
    },
    {
      "updateTime": 1781713800000,
      "tradeType": 1,
      "tag": "newListing",
      "tagsSimplified": "newListing",
      "categoriesTradeDataList": [
        {
          "timeRange": "m5",
          "timeParticleEnum": 5,
          "tradeInflow": "86855.49652899998"
        },
        {
          "timeRange": "m15",
          "timeParticleEnum": 15,
          "tradeInflow": "-127061.67766399994"
        },
        {
          "timeRange": "m30",
          "timeParticleEnum": 30,
          "tradeInflow": "-46370.814411000014"
        },
        {
          "timeRange": "H1",
          "timeParticleEnum": 101,
          "tradeInflow": "-790238.1811430001"
        },
        {
          "timeRange": "H2",
          "timeParticleEnum": 102,
          "tradeInflow": "1165976.910148999"
        },
        {
          "timeRange": "H4",
          "timeParticleEnum": 104,
          "tradeInflow": "1906196.9833620016"
        },
        {
          "timeRange": "H8",
          "timeParticleEnum": 108,
          "tradeInflow": "1550532.1490350007"
        },
        {
          "timeRange": "H12",
          "timeParticleEnum": 112,
          "tradeInflow": "2273819.3496840014"
        },
        {
          "timeRange": "H24",
          "timeParticleEnum": 124,
          "tradeInflow": "3697596.9207660006"
        },
        {
          "timeRange": "D2",
          "timeParticleEnum": 202,
          "tradeInflow": "9182256.122883001"
        },
        {
          "timeRange": "D3",
          "timeParticleEnum": 203,
          "tradeInflow": "8651010.984924002"
        },
        {
          "timeRange": "D5",
          "timeParticleEnum": 205,
          "tradeInflow": "9287386.036208002"
        },
        {
          "timeRange": "D7",
          "timeParticleEnum": 207,
          "tradeInflow": "745778.8311050012"
        },
        {
          "timeRange": "D10",
          "timeParticleEnum": 210,
          "tradeInflow": "-21597153.055995975"
        },
        {
          "timeRange": "D15",
          "timeParticleEnum": 215,
          "tradeInflow": "-28381607.21539"
        },
        {
          "timeRange": "D30",
          "timeParticleEnum": 230,
          "tradeInflow": "7240527.072372001"
        },
        {
          "timeRange": "D40",
          "timeParticleEnum": 240,
          "tradeInflow": "-182036141.296011"
        },
        {
          "timeRange": "D50",
          "timeParticleEnum": 250,
          "tradeInflow": "-261049180.22467"
        }
      ]
    },
    {
      "updateTime": 1781713800000,
      "tradeType": 1,
      "tag": "BSC",
      "tagsSimplified": "BSC",
      "categoriesTradeDataList": [
        {
          "timeRange": "m5",
          "timeParticleEnum": 5,
          "tradeInflow": "999985.2209332203"
        },
        {
          "timeRange": "m15",
          "timeParticleEnum": 15,
          "tradeInflow": "1073194.2171919104"
        },
        {
          "timeRange": "m30",
          "timeParticleEnum": 30,
          "tradeInflow": "1939633.5164619794"
        },
        {
          "timeRange": "H1",
          "timeParticleEnum": 101,
          "tradeInflow": "1895286.071526459"
        },
        {
          "timeRange": "H2",
          "timeParticleEnum": 102,
          "tradeInflow": "3768681.668986121"
        },
        {
          "timeRange": "H4",
          "timeParticleEnum": 104,
          "tradeInflow": "1542099.44167813"
        },
        {
          "timeRange": "H8",
          "timeParticleEnum": 108,
          "tradeInflow": "3513436.050212858"
        },
        {
          "timeRange": "H12",
          "timeParticleEnum": 112,
          "tradeInflow": "2018996.9804297881"
        },
        {
          "timeRange": "H24",
          "timeParticleEnum": 124,
          "tradeInflow": "-4320362.251961295"
        },
        {
          "timeRange": "D2",
          "timeParticleEnum": 202,
          "tradeInflow": "-38548899.31403438"
        },
        {
          "timeRange": "D3",
          "timeParticleEnum": 203,
          "tradeInflow": "-34403505.29981567"
        },
        {
          "timeRange": "D5",
          "timeParticleEnum": 205,
          "tradeInflow": "-48350671.593251035"
        },
        {
          "timeRange": "D7",
          "timeParticleEnum": 207,
          "tradeInflow": "-42812401.34577437"
        },
        {
          "timeRange": "D10",
          "timeParticleEnum": 210,
          "tradeInflow": "-45276388.67934022"
        },
        {
          "timeRange": "D15",
          "timeParticleEnum": 215,
          "tradeInflow": "-23998742.003515873"
        },
        {
          "timeRange": "D30",
          "timeParticleEnum": 230,
          "tradeInflow": "-109223279.23144369"
        },
        {
          "timeRange": "D40",
          "timeParticleEnum": 240,
          "tradeInflow": "-101950714.6681083"
        },
        {
          "timeRange": "D50",
          "timeParticleEnum": 250,
          "tradeInflow": "-135790477.96669957"
        },
        {
          "timeRange": "D60",
          "timeParticleEnum": 260,
          "tradeInflow": "-134738969.31175536"
        },
        {
          "timeRange": "D90",
          "timeParticleEnum": 290,
          "tradeInflow": "-144720776.21230665"
        },
        {
          "timeRange": "Y1",
          "timeParticleEnum": 401,
          "tradeInflow": "-1058257908.3176807"
        },
        {
          "timeRange": "Y2",
          "timeParticleEnum": 402,
          "tradeInflow": "-2034300160.0991402"
        },
        {
          "timeRange": "Y3",
          "timeParticleEnum": 403,
          "tradeInflow": "-3044571377.235787"
        },
        {
          "timeRange": "D120",
          "timeParticleEnum": 2120,
          "tradeInflow": "-160212880.86236387"
        },
        {
          "timeRange": "D150",
          "timeParticleEnum": 2150,
          "tradeInflow": "-386491202.66335505"
        },
        {
          "timeRange": "D180",
          "timeParticleEnum": 2180,
          "tradeInflow": "-406538366.19370294"
        }
      ]
    },
    {
      "updateTime": 1781713800000,
      "tradeType": 1,
      "tag": "Solana",
      "tagsSimplified": "Solana",
      "categoriesTradeDataList": [
        {
          "timeRange": "m5",
          "timeParticleEnum": 5,
          "tradeInflow": "1298586.47155882"
        },
        {
          "timeRange": "m15",
          "timeParticleEnum": 15,
          "tradeInflow": "1791245.8004922702"
        },
        {
          "timeRange": "m30",
          "timeParticleEnum": 30,
          "tradeInflow": "1721146.4511899205"
        },
        {
          "timeRange": "H1",
          "timeParticleEnum": 101,
          "tradeInflow": "4170212.7193781007"
        },
        {
          "timeRange": "H2",
          "timeParticleEnum": 102,
          "tradeInflow": "4032195.49163771"
        },
        {
          "timeRange": "H4",
          "timeParticleEnum": 104,
          "tradeInflow": "6717255.919653739"
        },
        {
          "timeRange": "H8",
          "timeParticleEnum": 108,
          "tradeInflow": "2891411.900161531"
        },
        {
          "timeRange": "H12",
          "timeParticleEnum": 112,
          "tradeInflow": "1318739.656204801"
        },
        {
          "timeRange": "H24",
          "timeParticleEnum": 124,
          "tradeInflow": "5308753.955124042"
        },
        {
          "timeRange": "D2",
          "timeParticleEnum": 202,
          "tradeInflow": "5026659.932926139"
        },
        {
          "timeRange": "D3",
          "timeParticleEnum": 203,
          "tradeInflow": "28477770.08144486"
        },
        {
          "timeRange": "D5",
          "timeParticleEnum": 205,
          "tradeInflow": "42729343.63604666"
        },
        {
          "timeRange": "D7",
          "timeParticleEnum": 207,
          "tradeInflow": "63297315.587228775"
        },
        {
          "timeRange": "D10",
          "timeParticleEnum": 210,
          "tradeInflow": "70045929.66239437"
        },
        {
          "timeRange": "D15",
          "timeParticleEnum": 215,
          "tradeInflow": "2237831.6794141186"
        },
        {
          "timeRange": "D30",
          "timeParticleEnum": 230,
          "tradeInflow": "45686174.89703945"
        },
        {
          "timeRange": "D40",
          "timeParticleEnum": 240,
          "tradeInflow": "36217042.31089717"
        },
        {
          "timeRange": "D50",
          "timeParticleEnum": 250,
          "tradeInflow": "81948176.69101971"
        },
        {
          "timeRange": "D60",
          "timeParticleEnum": 260,
          "tradeInflow": "146421116.61973512"
        },
        {
          "timeRange": "D90",
          "timeParticleEnum": 290,
          "tradeInflow": "292190259.6324662"
        },
        {
          "timeRange": "Y1",
          "timeParticleEnum": 401,
          "tradeInflow": "-2247269948.260098"
        },
        {
          "timeRange": "Y2",
          "timeParticleEnum": 402,
          "tradeInflow": "-4630377521.607074"
        },
        {
          "timeRange": "Y3",
          "timeParticleEnum": 403,
          "tradeInflow": "-2383653996.063795"
        },
        {
          "timeRange": "D120",
          "timeParticleEnum": 2120,
          "tradeInflow": "295870991.1327582"
        },
        {
          "timeRange": "D150",
          "timeParticleEnum": 2150,
          "tradeInflow": "41660036.36654825"
        },
        {
          "timeRange": "D180",
          "timeParticleEnum": 2180,
          "tradeInflow": "27635404.04125625"
        }
      ]
    },
    {
      "updateTime": 1781713800000,
      "tradeType": 1,
      "tag": "Launchpad",
      "tagsSimplified": "Launchpad",
      "categoriesTradeDataList": [
        {
          "timeRange": "m5",
          "timeParticleEnum": 5,
          "tradeInflow": "-16091.086770290016"
        },
        {
          "timeRange": "m15",
          "timeParticleEnum": 15,
          "tradeInflow": "-85186.00560778004"
        },
        {
          "timeRange": "m30",
          "timeParticleEnum": 30,
          "tradeInflow": "-213089.04997460006"
        },
        {
          "timeRange": "H1",
          "timeParticleEnum": 101,
          "tradeInflow": "-102735.74751304006"
        },
        {
          "timeRange": "H2",
          "timeParticleEnum": 102,
          "tradeInflow": "-308882.8525796401"
        },
        {
          "timeRange": "H4",
          "timeParticleEnum": 104,
          "tradeInflow": "-95807.61454675028"
        },
        {
          "timeRange": "H8",
          "timeParticleEnum": 108,
          "tradeInflow": "-892565.1127519399"
        },
        {
          "timeRange": "H12",
          "timeParticleEnum": 112,
          "tradeInflow": "-1080781.8952911897"
        },
        {
          "timeRange": "H24",
          "timeParticleEnum": 124,
          "tradeInflow": "-983379.8824612796"
        },
        {
          "timeRange": "D2",
          "timeParticleEnum": 202,
          "tradeInflow": "-1786084.3185674902"
        },
        {
          "timeRange": "D3",
          "timeParticleEnum": 203,
          "tradeInflow": "-2136335.4207459"
        },
        {
          "timeRange": "D5",
          "timeParticleEnum": 205,
          "tradeInflow": "-3235470.6879048995"
        },
        {
          "timeRange": "D7",
          "timeParticleEnum": 207,
          "tradeInflow": "-2715791.4532038006"
        },
        {
          "timeRange": "D10",
          "timeParticleEnum": 210,
          "tradeInflow": "-5577997.195295"
        },
        {
          "timeRange": "D15",
          "timeParticleEnum": 215,
          "tradeInflow": "-10689004.29499671"
        },
        {
          "timeRange": "D30",
          "timeParticleEnum": 230,
          "tradeInflow": "-14905650.127241729"
        },
        {
          "timeRange": "D40",
          "timeParticleEnum": 240,
          "tradeInflow": "-18978175.735332247"
        },
        {
          "timeRange": "D50",
          "timeParticleEnum": 250,
          "tradeInflow": "-19171663.6012634"
        },
        {
          "timeRange": "D60",
          "timeParticleEnum": 260,
          "tradeInflow": "-23777261.500337664"
        },
        {
          "timeRange": "D90",
          "timeParticleEnum": 290,
          "tradeInflow": "-23790496.543914933"
        },
        {
          "timeRange": "Y1",
          "timeParticleEnum": 401,
          "tradeInflow": "-502142240.81777906"
        },
        {
          "timeRange": "Y2",
          "timeParticleEnum": 402,
          "tradeInflow": "-1567427564.2870407"
        },
        {
          "timeRange": "Y3",
          "timeParticleEnum": 403,
          "tradeInflow": "-2278870397.5135674"
        },
        {
          "timeRange": "D120",
          "timeParticleEnum": 2120,
          "tradeInflow": "-28499960.908060573"
        },
        {
          "timeRange": "D150",
          "timeParticleEnum": 2150,
          "tradeInflow": "-55629222.91108961"
        },
        {
          "timeRange": "D180",
          "timeParticleEnum": 2180,
          "tradeInflow": "-72764043.544767"
        }
      ]
    },
    {
      "updateTime": 1781713800000,
      "tradeType": 1,
      "tag": "pos",
      "tagsSimplified": "pos",
      "categoriesTradeDataList": [
        {
          "timeRange": "m5",
          "timeParticleEnum": 5,
          "tradeInflow": "5299288.459193895"
        },
        {
          "timeRange": "m15",
          "timeParticleEnum": 15,
          "tradeInflow": "3509184.6653955774"
        },
        {
          "timeRange": "m30",
          "timeParticleEnum": 30,
          "tradeInflow": "4191053.699156929"
        },
        {
          "timeRange": "H1",
          "timeParticleEnum": 101,
          "tradeInflow": "9839959.390944075"
        },
        {
          "timeRange": "H2",
          "timeParticleEnum": 102,
          "tradeInflow": "2181532.915237591"
        },
        {
          "timeRange": "H4",
          "timeParticleEnum": 104,
          "tradeInflow": "-7855608.898768899"
        },
        {
          "timeRange": "H8",
          "timeParticleEnum": 108,
          "tradeInflow": "-24108886.46520988"
        },
        {
          "timeRange": "H12",
          "timeParticleEnum": 112,
          "tradeInflow": "-26279258.66196451"
        },
        {
          "timeRange": "H24",
          "timeParticleEnum": 124,
          "tradeInflow": "-12967840.012158444"
        },
        {
          "timeRange": "D2",
          "timeParticleEnum": 202,
          "tradeInflow": "-80274468.82614458"
        },
        {
          "timeRange": "D3",
          "timeParticleEnum": 203,
          "tradeInflow": "-46075525.04478877"
        },
        {
          "timeRange": "D5",
          "timeParticleEnum": 205,
          "tradeInflow": "-11230760.427819775"
        },
        {
          "timeRange": "D7",
          "timeParticleEnum": 207,
          "tradeInflow": "74760488.41687685"
        },
        {
          "timeRange": "D10",
          "timeParticleEnum": 210,
          "tradeInflow": "23834789.175114848"
        },
        {
          "timeRange": "D15",
          "timeParticleEnum": 215,
          "tradeInflow": "-190311156.06828627"
        },
        {
          "timeRange": "D30",
          "timeParticleEnum": 230,
          "tradeInflow": "-390149250.0932093"
        },
        {
          "timeRange": "D40",
          "timeParticleEnum": 240,
          "tradeInflow": "-903882749.1637864"
        },
        {
          "timeRange": "D50",
          "timeParticleEnum": 250,
          "tradeInflow": "-1338250821.9540043"
        },
        {
          "timeRange": "D60",
          "timeParticleEnum": 260,
          "tradeInflow": "-1535053380.7953591"
        },
        {
          "timeRange": "D90",
          "timeParticleEnum": 290,
          "tradeInflow": "-1561380080.182936"
        },
        {
          "timeRange": "Y1",
          "timeParticleEnum": 401,
          "tradeInflow": "-16696713507.922045"
        },
        {
          "timeRange": "Y2",
          "timeParticleEnum": 402,
          "tradeInflow": "-26087957853.564915"
        },
        {
          "timeRange": "Y3",
          "timeParticleEnum": 403,
          "tradeInflow": "-29886898910.82368"
        },
        {
          "timeRange": "D120",
          "timeParticleEnum": 2120,
          "tradeInflow": "-1773009894.309904"
        },
        {
          "timeRange": "D150",
          "timeParticleEnum": 2150,
          "tradeInflow": "-3838449148.594717"
        },
        {
          "timeRange": "D180",
          "timeParticleEnum": 2180,
          "tradeInflow": "-3665726818.3483257"
        }
      ]
    },
    {
      "updateTime": 1781713800000,
      "tradeType": 1,
      "tag": "Infrastructure",
      "tagsSimplified": "基础架构",
      "categoriesTradeDataList": [
        {
          "timeRange": "m5",
          "timeParticleEnum": 5,
          "tradeInflow": "72097.31988172994"
        },
        {
          "timeRange": "m15",
          "timeParticleEnum": 15,
          "tradeInflow": "-88890.28127362"
        },
        {
          "timeRange": "m30",
          "timeParticleEnum": 30,
          "tradeInflow": "-251675.98255318"
        },
        {
          "timeRange": "H1",
          "timeParticleEnum": 101,
          "tradeInflow": "-139161.5807380702"
        },
        {
          "timeRange": "H2",
          "timeParticleEnum": 102,
          "tradeInflow": "-108269.86624405059"
        },
        {
          "timeRange": "H4",
          "timeParticleEnum": 104,
          "tradeInflow": "-4751514.708771689"
        },
        {
          "timeRange": "H8",
          "timeParticleEnum": 108,
          "tradeInflow": "-14290877.007736025"
        },
        {
          "timeRange": "H12",
          "timeParticleEnum": 112,
          "tradeInflow": "-20030137.815907955"
        },
        {
          "timeRange": "H24",
          "timeParticleEnum": 124,
          "tradeInflow": "-16229313.733073324"
        },
        {
          "timeRange": "D2",
          "timeParticleEnum": 202,
          "tradeInflow": "-28892990.541205727"
        },
        {
          "timeRange": "D3",
          "timeParticleEnum": 203,
          "tradeInflow": "-47237544.19727902"
        },
        {
          "timeRange": "D5",
          "timeParticleEnum": 205,
          "tradeInflow": "-48491800.82359166"
        },
        {
          "timeRange": "D7",
          "timeParticleEnum": 207,
          "tradeInflow": "-47932221.85037526"
        },
        {
          "timeRange": "D10",
          "timeParticleEnum": 210,
          "tradeInflow": "-57488619.213998824"
        },
        {
          "timeRange": "D15",
          "timeParticleEnum": 215,
          "tradeInflow": "-74292457.28102437"
        },
        {
          "timeRange": "D30",
          "timeParticleEnum": 230,
          "tradeInflow": "-111845306.34763205"
        },
        {
          "timeRange": "D40",
          "timeParticleEnum": 240,
          "tradeInflow": "-134696072.79522827"
        },
        {
          "timeRange": "D50",
          "timeParticleEnum": 250,
          "tradeInflow": "-161313122.79843685"
        },
        {
          "timeRange": "D60",
          "timeParticleEnum": 260,
          "tradeInflow": "-170903030.08614278"
        },
        {
          "timeRange": "D90",
          "timeParticleEnum": 290,
          "tradeInflow": "-379681616.5091822"
        },
        {
          "timeRange": "Y1",
          "timeParticleEnum": 401,
          "tradeInflow": "-1701170674.2955866"
        },
        {
          "timeRange": "Y2",
          "timeParticleEnum": 402,
          "tradeInflow": "-4773656221.675263"
        },
        {
          "timeRange": "Y3",
          "timeParticleEnum": 403,
          "tradeInflow": "-3765831471.1454587"
        },
        {
          "timeRange": "D120",
          "timeParticleEnum": 2120,
          "tradeInflow": "-229728181.30781302"
        },
        {
          "timeRange": "D150",
          "timeParticleEnum": 2150,
          "tradeInflow": "-705276777.3670734"
        },
        {
          "timeRange": "D180",
          "timeParticleEnum": 2180,
          "tradeInflow": "-389293265.79596317"
        }
      ]
    },
    {
      "updateTime": 1781713800000,
      "tradeType": 1,
      "tag": "Megadrop",
      "tagsSimplified": "Megadrop",
      "categoriesTradeDataList": [
        {
          "timeRange": "m5",
          "timeParticleEnum": 5,
          "tradeInflow": "383.3941999999992"
        },
        {
          "timeRange": "m15",
          "timeParticleEnum": 15,
          "tradeInflow": "3109.31063"
        },
        {
          "timeRange": "m30",
          "timeParticleEnum": 30,
          "tradeInflow": "-2540.4853200000007"
        },
        {
          "timeRange": "H1",
          "timeParticleEnum": 101,
          "tradeInflow": "6733.288950000002"
        },
        {
          "timeRange": "H2",
          "timeParticleEnum": 102,
          "tradeInflow": "4556.27077"
        },
        {
          "timeRange": "H4",
          "timeParticleEnum": 104,
          "tradeInflow": "18401.31909"
        },
        {
          "timeRange": "H8",
          "timeParticleEnum": 108,
          "tradeInflow": "34980.35584"
        },
        {
          "timeRange": "H12",
          "timeParticleEnum": 112,
          "tradeInflow": "64880.13639"
        },
        {
          "timeRange": "H24",
          "timeParticleEnum": 124,
          "tradeInflow": "47583.64622999999"
        },
        {
          "timeRange": "D2",
          "timeParticleEnum": 202,
          "tradeInflow": "17065.34660000001"
        },
        {
          "timeRange": "D3",
          "timeParticleEnum": 203,
          "tradeInflow": "52328.18007999998"
        },
        {
          "timeRange": "D5",
          "timeParticleEnum": 205,
          "tradeInflow": "-3557.343600000197"
        },
        {
          "timeRange": "D7",
          "timeParticleEnum": 207,
          "tradeInflow": "-83313.53469000022"
        },
        {
          "timeRange": "D10",
          "timeParticleEnum": 210,
          "tradeInflow": "-197812.96592000013"
        },
        {
          "timeRange": "D15",
          "timeParticleEnum": 215,
          "tradeInflow": "-520399.63795999996"
        },
        {
          "timeRange": "D30",
          "timeParticleEnum": 230,
          "tradeInflow": "-779636.6958100001"
        },
        {
          "timeRange": "D40",
          "timeParticleEnum": 240,
          "tradeInflow": "349482.33986000053"
        },
        {
          "timeRange": "D50",
          "timeParticleEnum": 250,
          "tradeInflow": "1280241.7074400012"
        },
        {
          "timeRange": "D60",
          "timeParticleEnum": 260,
          "tradeInflow": "1805564.3578400016"
        },
        {
          "timeRange": "D90",
          "timeParticleEnum": 290,
          "tradeInflow": "-823639.4892099963"
        },
        {
          "timeRange": "Y1",
          "timeParticleEnum": 401,
          "tradeInflow": "-118455621.01869"
        },
        {
          "timeRange": "Y2",
          "timeParticleEnum": 402,
          "tradeInflow": "-116977921.47049999"
        },
        {
          "timeRange": "D120",
          "timeParticleEnum": 2120,
          "tradeInflow": "-731744.500779997"
        },
        {
          "timeRange": "D150",
          "timeParticleEnum": 2150,
          "tradeInflow": "-1105099.7623699966"
        },
        {
          "timeRange": "D180",
          "timeParticleEnum": 2180,
          "tradeInflow": "-3113531.1941299974"
        }
      ]
    },
    {
      "updateTime": 1781713800000,
      "tradeType": 1,
      "tag": "tCommodities",
      "tagsSimplified": "tCommodities",
      "categoriesTradeDataList": [
        {
          "timeRange": "m5",
          "timeParticleEnum": 5,
          "tradeInflow": "-472.049091999996"
        },
        {
          "timeRange": "m15",
          "timeParticleEnum": 15,
          "tradeInflow": "157693.77700600002"
        },
        {
          "timeRange": "m30",
          "timeParticleEnum": 30,
          "tradeInflow": "297190.807058"
        },
        {
          "timeRange": "H1",
          "timeParticleEnum": 101,
          "tradeInflow": "129526.22091799993"
        },
        {
          "timeRange": "H2",
          "timeParticleEnum": 102,
          "tradeInflow": "235593.07598099977"
        },
        {
          "timeRange": "H4",
          "timeParticleEnum": 104,
          "tradeInflow": "721809.1874649994"
        },
        {
          "timeRange": "H8",
          "timeParticleEnum": 108,
          "tradeInflow": "-5005306.942033005"
        },
        {
          "timeRange": "H12",
          "timeParticleEnum": 112,
          "tradeInflow": "-5931403.463740004"
        },
        {
          "timeRange": "H24",
          "timeParticleEnum": 124,
          "tradeInflow": "-6399120.052663999"
        },
        {
          "timeRange": "D2",
          "timeParticleEnum": 202,
          "tradeInflow": "-2531797.869536995"
        },
        {
          "timeRange": "D3",
          "timeParticleEnum": 203,
          "tradeInflow": "-745845.001409"
        },
        {
          "timeRange": "D5",
          "timeParticleEnum": 205,
          "tradeInflow": "-5532342.250542998"
        },
        {
          "timeRange": "D7",
          "timeParticleEnum": 207,
          "tradeInflow": "-22894607.430146"
        },
        {
          "timeRange": "D10",
          "timeParticleEnum": 210,
          "tradeInflow": "-28712169.235471997"
        },
        {
          "timeRange": "D15",
          "timeParticleEnum": 215,
          "tradeInflow": "-39621219.555512995"
        },
        {
          "timeRange": "D30",
          "timeParticleEnum": 230,
          "tradeInflow": "-59253669.678720005"
        },
        {
          "timeRange": "D40",
          "timeParticleEnum": 240,
          "tradeInflow": "-63493781.830965996"
        },
        {
          "timeRange": "D50",
          "timeParticleEnum": 250,
          "tradeInflow": "-62223600.75242901"
        },
        {
          "timeRange": "D60",
          "timeParticleEnum": 260,
          "tradeInflow": "-68450791.72269599"
        },
        {
          "timeRange": "D90",
          "timeParticleEnum": 290,
          "tradeInflow": "-35124512.153349966"
        },
        {
          "timeRange": "Y1",
          "timeParticleEnum": 401,
          "tradeInflow": "-749047043.730638"
        },
        {
          "timeRange": "Y2",
          "timeParticleEnum": 402,
          "tradeInflow": "-808255789.7220082"
        },
        {
          "timeRange": "Y3",
          "timeParticleEnum": 403,
          "tradeInflow": "-843287219.5254743"
        },
        {
          "timeRange": "D120",
          "timeParticleEnum": 2120,
          "tradeInflow": "-155927528.97948095"
        },
        {
          "timeRange": "D150",
          "timeParticleEnum": 2150,
          "tradeInflow": "-360449406.21793306"
        },
        {
          "timeRange": "D180",
          "timeParticleEnum": 2180,
          "tradeInflow": "-453479972.9171699"
        }
      ]
    },
    {
      "updateTime": 1781713800000,
      "tradeType": 1,
      "tag": "NFT",
      "tagsSimplified": "NFT",
      "categoriesTradeDataList": [
        {
          "timeRange": "m5",
          "timeParticleEnum": 5,
          "tradeInflow": "46344.150697000034"
        },
        {
          "timeRange": "m15",
          "timeParticleEnum": 15,
          "tradeInflow": "47375.200625000034"
        },
        {
          "timeRange": "m30",
          "timeParticleEnum": 30,
          "tradeInflow": "63857.36601200003"
        },
        {
          "timeRange": "H1",
          "timeParticleEnum": 101,
          "tradeInflow": "122712.23847300005"
        },
        {
          "timeRange": "H2",
          "timeParticleEnum": 102,
          "tradeInflow": "113158.43843600005"
        },
        {
          "timeRange": "H4",
          "timeParticleEnum": 104,
          "tradeInflow": "94732.26535800008"
        },
        {
          "timeRange": "H8",
          "timeParticleEnum": 108,
          "tradeInflow": "-198801.62264800002"
        },
        {
          "timeRange": "H12",
          "timeParticleEnum": 112,
          "tradeInflow": "-202038.1478880001"
        },
        {
          "timeRange": "H24",
          "timeParticleEnum": 124,
          "tradeInflow": "53601.23122999989"
        },
        {
          "timeRange": "D2",
          "timeParticleEnum": 202,
          "tradeInflow": "-62690.24388400086"
        },
        {
          "timeRange": "D3",
          "timeParticleEnum": 203,
          "tradeInflow": "247086.80993299893"
        },
        {
          "timeRange": "D5",
          "timeParticleEnum": 205,
          "tradeInflow": "-867548.660267"
        },
        {
          "timeRange": "D7",
          "timeParticleEnum": 207,
          "tradeInflow": "-3117920.7539279996"
        },
        {
          "timeRange": "D10",
          "timeParticleEnum": 210,
          "tradeInflow": "-6597116.583380001"
        },
        {
          "timeRange": "D15",
          "timeParticleEnum": 215,
          "tradeInflow": "-12934257.69542"
        },
        {
          "timeRange": "D30",
          "timeParticleEnum": 230,
          "tradeInflow": "-25438815.50310299"
        },
        {
          "timeRange": "D40",
          "timeParticleEnum": 240,
          "tradeInflow": "-37375878.136074"
        },
        {
          "timeRange": "D50",
          "timeParticleEnum": 250,
          "tradeInflow": "-42516808.26230499"
        },
        {
          "timeRange": "D60",
          "timeParticleEnum": 260,
          "tradeInflow": "-48952412.68494499"
        },
        {
          "timeRange": "D90",
          "timeParticleEnum": 290,
          "tradeInflow": "-23004794.379504994"
        },
        {
          "timeRange": "Y1",
          "timeParticleEnum": 401,
          "tradeInflow": "-208983198.91116193"
        },
        {
          "timeRange": "Y2",
          "timeParticleEnum": 402,
          "tradeInflow": "-900328199.490995"
        },
        {
          "timeRange": "Y3",
          "timeParticleEnum": 403,
          "tradeInflow": "-1848271026.252079"
        },
        {
          "timeRange": "D120",
          "timeParticleEnum": 2120,
          "tradeInflow": "-22129246.714580987"
        },
        {
          "timeRange": "D150",
          "timeParticleEnum": 2150,
          "tradeInflow": "-34131902.21195798"
        },
        {
          "timeRange": "D180",
          "timeParticleEnum": 2180,
          "tradeInflow": "-41571924.50079198"
        }
      ]
    },
    {
      "updateTime": 1781713800000,
      "tradeType": 1,
      "tag": "RWA",
      "tagsSimplified": "RWA",
      "categoriesTradeDataList": [
        {
          "timeRange": "m5",
          "timeParticleEnum": 5,
          "tradeInflow": "209612.6502026"
        },
        {
          "timeRange": "m15",
          "timeParticleEnum": 15,
          "tradeInflow": "232471.95862200003"
        },
        {
          "timeRange": "m30",
          "timeParticleEnum": 30,
          "tradeInflow": "325931.3637739"
        },
        {
          "timeRange": "H1",
          "timeParticleEnum": 101,
          "tradeInflow": "1116392.1853132003"
        },
        {
          "timeRange": "H2",
          "timeParticleEnum": 102,
          "tradeInflow": "946275.5399362002"
        },
        {
          "timeRange": "H4",
          "timeParticleEnum": 104,
          "tradeInflow": "1763756.7931086"
        },
        {
          "timeRange": "H8",
          "timeParticleEnum": 108,
          "tradeInflow": "342636.36717800034"
        },
        {
          "timeRange": "H12",
          "timeParticleEnum": 112,
          "tradeInflow": "223090.9509211"
        },
        {
          "timeRange": "H24",
          "timeParticleEnum": 124,
          "tradeInflow": "838843.4599110003"
        },
        {
          "timeRange": "D2",
          "timeParticleEnum": 202,
          "tradeInflow": "-1265954.6887958"
        },
        {
          "timeRange": "D3",
          "timeParticleEnum": 203,
          "tradeInflow": "905553.0450562993"
        },
        {
          "timeRange": "D5",
          "timeParticleEnum": 205,
          "tradeInflow": "417029.06890520046"
        },
        {
          "timeRange": "D7",
          "timeParticleEnum": 207,
          "tradeInflow": "-162917.26698930043"
        },
        {
          "timeRange": "D10",
          "timeParticleEnum": 210,
          "tradeInflow": "-4986555.852731502"
        },
        {
          "timeRange": "D15",
          "timeParticleEnum": 215,
          "tradeInflow": "-30890882.342218004"
        },
        {
          "timeRange": "D30",
          "timeParticleEnum": 230,
          "tradeInflow": "-63064678.00158283"
        },
        {
          "timeRange": "D40",
          "timeParticleEnum": 240,
          "tradeInflow": "-66180410.0075092"
        },
        {
          "timeRange": "D50",
          "timeParticleEnum": 250,
          "tradeInflow": "-75002314.3622227"
        },
        {
          "timeRange": "D60",
          "timeParticleEnum": 260,
          "tradeInflow": "-85065988.41740851"
        },
        {
          "timeRange": "D90",
          "timeParticleEnum": 290,
          "tradeInflow": "-134786053.36367032"
        },
        {
          "timeRange": "Y1",
          "timeParticleEnum": 401,
          "tradeInflow": "-1693312602.5118234"
        },
        {
          "timeRange": "Y2",
          "timeParticleEnum": 402,
          "tradeInflow": "-3237466408.6324177"
        },
        {
          "timeRange": "Y3",
          "timeParticleEnum": 403,
          "tradeInflow": "-4327096132.318716"
        },
        {
          "timeRange": "D120",
          "timeParticleEnum": 2120,
          "tradeInflow": "-89345027.87154192"
        },
        {
          "timeRange": "D150",
          "timeParticleEnum": 2150,
          "tradeInflow": "-237859519.6249414"
        },
        {
          "timeRange": "D180",
          "timeParticleEnum": 2180,
          "tradeInflow": "-316273081.71255577"
        }
      ]
    },
    {
      "updateTime": 1781713800000,
      "tradeType": 1,
      "tag": "Monitoring",
      "tagsSimplified": "观察",
      "categoriesTradeDataList": [
        {
          "timeRange": "m5",
          "timeParticleEnum": 5,
          "tradeInflow": "1520.2607846000003"
        },
        {
          "timeRange": "m15",
          "timeParticleEnum": 15,
          "tradeInflow": "28452.673735300006"
        },
        {
          "timeRange": "m30",
          "timeParticleEnum": 30,
          "tradeInflow": "60800.45443059998"
        },
        {
          "timeRange": "H1",
          "timeParticleEnum": 101,
          "tradeInflow": "68135.8512266"
        },
        {
          "timeRange": "H2",
          "timeParticleEnum": 102,
          "tradeInflow": "98356.37057120004"
        },
        {
          "timeRange": "H4",
          "timeParticleEnum": 104,
          "tradeInflow": "-88840.7198353001"
        },
        {
          "timeRange": "H8",
          "timeParticleEnum": 108,
          "tradeInflow": "-645305.4390980001"
        },
        {
          "timeRange": "H12",
          "timeParticleEnum": 112,
          "tradeInflow": "-442245.8672382999"
        },
        {
          "timeRange": "H24",
          "timeParticleEnum": 124,
          "tradeInflow": "-170769.54634209978"
        },
        {
          "timeRange": "D2",
          "timeParticleEnum": 202,
          "tradeInflow": "-751954.6560594998"
        },
        {
          "timeRange": "D3",
          "timeParticleEnum": 203,
          "tradeInflow": "-1359756.4580718998"
        },
        {
          "timeRange": "D5",
          "timeParticleEnum": 205,
          "tradeInflow": "-2665830.529519399"
        },
        {
          "timeRange": "D7",
          "timeParticleEnum": 207,
          "tradeInflow": "-3525785.630007899"
        },
        {
          "timeRange": "D10",
          "timeParticleEnum": 210,
          "tradeInflow": "-4871274.994611498"
        },
        {
          "timeRange": "D15",
          "timeParticleEnum": 215,
          "tradeInflow": "-6461865.7972457"
        },
        {
          "timeRange": "D30",
          "timeParticleEnum": 230,
          "tradeInflow": "-14255508.307997398"
        },
        {
          "timeRange": "D40",
          "timeParticleEnum": 240,
          "tradeInflow": "-14289258.454863898"
        },
        {
          "timeRange": "D50",
          "timeParticleEnum": 250,
          "tradeInflow": "-13907773.827289304"
        },
        {
          "timeRange": "D60",
          "timeParticleEnum": 260,
          "tradeInflow": "-25965603.732308403"
        },
        {
          "timeRange": "D90",
          "timeParticleEnum": 290,
          "tradeInflow": "-28255228.957854092"
        },
        {
          "timeRange": "Y1",
          "timeParticleEnum": 401,
          "tradeInflow": "-282136066.9360881"
        },
        {
          "timeRange": "Y2",
          "timeParticleEnum": 402,
          "tradeInflow": "-1028447459.0938265"
        },
        {
          "timeRange": "Y3",
          "timeParticleEnum": 403,
          "tradeInflow": "-932177063.9068127"
        },
        {
          "timeRange": "D120",
          "timeParticleEnum": 2120,
          "tradeInflow": "-31925207.851828698"
        },
        {
          "timeRange": "D150",
          "timeParticleEnum": 2150,
          "tradeInflow": "-38679400.10153931"
        },
        {
          "timeRange": "D180",
          "timeParticleEnum": 2180,
          "tradeInflow": "-51891543.319786295"
        }
      ]
    },
    {
      "updateTime": 1781713800000,
      "tradeType": 1,
      "tag": "Launchpool",
      "tagsSimplified": "Launchpool",
      "categoriesTradeDataList": [
        {
          "timeRange": "m5",
          "timeParticleEnum": 5,
          "tradeInflow": "98882.22715100007"
        },
        {
          "timeRange": "m15",
          "timeParticleEnum": 15,
          "tradeInflow": "117969.78924560004"
        },
        {
          "timeRange": "m30",
          "timeParticleEnum": 30,
          "tradeInflow": "282121.69575189997"
        },
        {
          "timeRange": "H1",
          "timeParticleEnum": 101,
          "tradeInflow": "837944.0018189994"
        },
        {
          "timeRange": "H2",
          "timeParticleEnum": 102,
          "tradeInflow": "1150953.5174225995"
        },
        {
          "timeRange": "H4",
          "timeParticleEnum": 104,
          "tradeInflow": "1624419.1257141994"
        },
        {
          "timeRange": "H8",
          "timeParticleEnum": 108,
          "tradeInflow": "921661.3877196995"
        },
        {
          "timeRange": "H12",
          "timeParticleEnum": 112,
          "tradeInflow": "1286125.8883477997"
        },
        {
          "timeRange": "H24",
          "timeParticleEnum": 124,
          "tradeInflow": "609733.0716915004"
        },
        {
          "timeRange": "D2",
          "timeParticleEnum": 202,
          "tradeInflow": "-5072882.7313541"
        },
        {
          "timeRange": "D3",
          "timeParticleEnum": 203,
          "tradeInflow": "1080243.738000699"
        },
        {
          "timeRange": "D5",
          "timeParticleEnum": 205,
          "tradeInflow": "-5187031.365308203"
        },
        {
          "timeRange": "D7",
          "timeParticleEnum": 207,
          "tradeInflow": "-31819356.766030908"
        },
        {
          "timeRange": "D10",
          "timeParticleEnum": 210,
          "tradeInflow": "-53749867.37054271"
        },
        {
          "timeRange": "D15",
          "timeParticleEnum": 215,
          "tradeInflow": "-77481825.4783502"
        },
        {
          "timeRange": "D30",
          "timeParticleEnum": 230,
          "tradeInflow": "-160606825.82462788"
        },
        {
          "timeRange": "D40",
          "timeParticleEnum": 240,
          "tradeInflow": "-251829113.59250382"
        },
        {
          "timeRange": "D50",
          "timeParticleEnum": 250,
          "tradeInflow": "-313056687.4644944"
        },
        {
          "timeRange": "D60",
          "timeParticleEnum": 260,
          "tradeInflow": "-326259852.42168397"
        },
        {
          "timeRange": "D90",
          "timeParticleEnum": 290,
          "tradeInflow": "-361734478.3188189"
        },
        {
          "timeRange": "Y1",
          "timeParticleEnum": 401,
          "tradeInflow": "-2634873899.0835767"
        },
        {
          "timeRange": "Y2",
          "timeParticleEnum": 402,
          "tradeInflow": "-4236438453.567979"
        },
        {
          "timeRange": "Y3",
          "timeParticleEnum": 403,
          "tradeInflow": "-1602858109.7930524"
        },
        {
          "timeRange": "D120",
          "timeParticleEnum": 2120,
          "tradeInflow": "-362154609.82297206"
        },
        {
          "timeRange": "D150",
          "timeParticleEnum": 2150,
          "tradeInflow": "-429750677.0083209"
        },
        {
          "timeRange": "D180",
          "timeParticleEnum": 2180,
          "tradeInflow": "-510407114.4470358"
        }
      ]
    },
    {
      "updateTime": 1781713800000,
      "tradeType": 1,
      "tag": "innovation-zone",
      "tagsSimplified": "innovation-zone",
      "categoriesTradeDataList": [
        {
          "timeRange": "m5",
          "timeParticleEnum": 5,
          "tradeInflow": "135442.70191940997"
        },
        {
          "timeRange": "m15",
          "timeParticleEnum": 15,
          "tradeInflow": "72819.05268900999"
        },
        {
          "timeRange": "m30",
          "timeParticleEnum": 30,
          "tradeInflow": "38954.8633302"
        },
        {
          "timeRange": "H1",
          "timeParticleEnum": 101,
          "tradeInflow": "129562.90523257006"
        },
        {
          "timeRange": "H2",
          "timeParticleEnum": 102,
          "tradeInflow": "-200072.57984679993"
        },
        {
          "timeRange": "H4",
          "timeParticleEnum": 104,
          "tradeInflow": "18202.67123545999"
        },
        {
          "timeRange": "H8",
          "timeParticleEnum": 108,
          "tradeInflow": "-395587.1570661805"
        },
        {
          "timeRange": "H12",
          "timeParticleEnum": 112,
          "tradeInflow": "264326.7729590199"
        },
        {
          "timeRange": "H24",
          "timeParticleEnum": 124,
          "tradeInflow": "2055742.12632752"
        },
        {
          "timeRange": "D2",
          "timeParticleEnum": 202,
          "tradeInflow": "1248243.6271993602"
        },
        {
          "timeRange": "D3",
          "timeParticleEnum": 203,
          "tradeInflow": "3578519.7424995103"
        },
        {
          "timeRange": "D5",
          "timeParticleEnum": 205,
          "tradeInflow": "1885077.9023937562"
        },
        {
          "timeRange": "D7",
          "timeParticleEnum": 207,
          "tradeInflow": "2394444.801175256"
        },
        {
          "timeRange": "D10",
          "timeParticleEnum": 210,
          "tradeInflow": "4249030.043700318"
        },
        {
          "timeRange": "D15",
          "timeParticleEnum": 215,
          "tradeInflow": "556095.4724952644"
        },
        {
          "timeRange": "D30",
          "timeParticleEnum": 230,
          "tradeInflow": "-5602824.549750829"
        },
        {
          "timeRange": "D40",
          "timeParticleEnum": 240,
          "tradeInflow": "-20441597.37263325"
        },
        {
          "timeRange": "D50",
          "timeParticleEnum": 250,
          "tradeInflow": "-18815694.223669425"
        },
        {
          "timeRange": "D60",
          "timeParticleEnum": 260,
          "tradeInflow": "-25473528.227682468"
        },
        {
          "timeRange": "D90",
          "timeParticleEnum": 290,
          "tradeInflow": "-33450211.769867823"
        },
        {
          "timeRange": "Y1",
          "timeParticleEnum": 401,
          "tradeInflow": "-722975332.0616341"
        },
        {
          "timeRange": "Y2",
          "timeParticleEnum": 402,
          "tradeInflow": "-1989071516.5152085"
        },
        {
          "timeRange": "Y3",
          "timeParticleEnum": 403,
          "tradeInflow": "-2257928647.4864793"
        },
        {
          "timeRange": "D120",
          "timeParticleEnum": 2120,
          "tradeInflow": "-58390894.71115862"
        },
        {
          "timeRange": "D150",
          "timeParticleEnum": 2150,
          "tradeInflow": "-68716656.2629676"
        },
        {
          "timeRange": "D180",
          "timeParticleEnum": 2180,
          "tradeInflow": "-106482502.51506925"
        }
      ]
    },
    {
      "updateTime": 1781713800000,
      "tradeType": 1,
      "tag": "AI",
      "tagsSimplified": "AI",
      "categoriesTradeDataList": [
        {
          "timeRange": "m5",
          "timeParticleEnum": 5,
          "tradeInflow": "-46004.04284800008"
        },
        {
          "timeRange": "m15",
          "timeParticleEnum": 15,
          "tradeInflow": "-121112.4431250001"
        },
        {
          "timeRange": "m30",
          "timeParticleEnum": 30,
          "tradeInflow": "6218.866097999976"
        },
        {
          "timeRange": "H1",
          "timeParticleEnum": 101,
          "tradeInflow": "651209.9179929999"
        },
        {
          "timeRange": "H2",
          "timeParticleEnum": 102,
          "tradeInflow": "386664.3113239997"
        },
        {
          "timeRange": "H4",
          "timeParticleEnum": 104,
          "tradeInflow": "776479.5177559996"
        },
        {
          "timeRange": "H8",
          "timeParticleEnum": 108,
          "tradeInflow": "-818969.4668550001"
        },
        {
          "timeRange": "H12",
          "timeParticleEnum": 112,
          "tradeInflow": "-1916792.835324999"
        },
        {
          "timeRange": "H24",
          "timeParticleEnum": 124,
          "tradeInflow": "-2381384.626754"
        },
        {
          "timeRange": "D2",
          "timeParticleEnum": 202,
          "tradeInflow": "-20213200.771228"
        },
        {
          "timeRange": "D3",
          "timeParticleEnum": 203,
          "tradeInflow": "-40152226.28017301"
        },
        {
          "timeRange": "D5",
          "timeParticleEnum": 205,
          "tradeInflow": "-42402061.88551901"
        },
        {
          "timeRange": "D7",
          "timeParticleEnum": 207,
          "tradeInflow": "-41876186.74501202"
        },
        {
          "timeRange": "D10",
          "timeParticleEnum": 210,
          "tradeInflow": "-57767913.92265502"
        },
        {
          "timeRange": "D15",
          "timeParticleEnum": 215,
          "tradeInflow": "-82280255.52851205"
        },
        {
          "timeRange": "D30",
          "timeParticleEnum": 230,
          "tradeInflow": "-157473676.69376406"
        },
        {
          "timeRange": "D40",
          "timeParticleEnum": 240,
          "tradeInflow": "-394080325.75857"
        },
        {
          "timeRange": "D50",
          "timeParticleEnum": 250,
          "tradeInflow": "-467423066.94499505"
        },
        {
          "timeRange": "D60",
          "timeParticleEnum": 260,
          "tradeInflow": "-220730955.07838002"
        },
        {
          "timeRange": "D90",
          "timeParticleEnum": 290,
          "tradeInflow": "-511627494.890389"
        },
        {
          "timeRange": "Y1",
          "timeParticleEnum": 401,
          "tradeInflow": "-2327880659.966795"
        },
        {
          "timeRange": "Y2",
          "timeParticleEnum": 402,
          "tradeInflow": "-5196838010.700582"
        },
        {
          "timeRange": "Y3",
          "timeParticleEnum": 403,
          "tradeInflow": "-4435610721.235427"
        },
        {
          "timeRange": "D120",
          "timeParticleEnum": 2120,
          "tradeInflow": "-401328658.63747406"
        },
        {
          "timeRange": "D150",
          "timeParticleEnum": 2150,
          "tradeInflow": "-482586593.5506201"
        },
        {
          "timeRange": "D180",
          "timeParticleEnum": 2180,
          "tradeInflow": "-587748874.4009951"
        }
      ]
    },
    {
      "updateTime": 1781713800000,
      "tradeType": 1,
      "tag": "defi",
      "tagsSimplified": "DeFi",
      "categoriesTradeDataList": [
        {
          "timeRange": "m5",
          "timeParticleEnum": 5,
          "tradeInflow": "438987.67833278456"
        },
        {
          "timeRange": "m15",
          "timeParticleEnum": 15,
          "tradeInflow": "540540.2823800578"
        },
        {
          "timeRange": "m30",
          "timeParticleEnum": 30,
          "tradeInflow": "1571066.9010415273"
        },
        {
          "timeRange": "H1",
          "timeParticleEnum": 101,
          "tradeInflow": "2003547.0372690153"
        },
        {
          "timeRange": "H2",
          "timeParticleEnum": 102,
          "tradeInflow": "3153922.012644525"
        },
        {
          "timeRange": "H4",
          "timeParticleEnum": 104,
          "tradeInflow": "5111185.610176649"
        },
        {
          "timeRange": "H8",
          "timeParticleEnum": 108,
          "tradeInflow": "7495992.099838442"
        },
        {
          "timeRange": "H12",
          "timeParticleEnum": 112,
          "tradeInflow": "8456261.678400967"
        },
        {
          "timeRange": "H24",
          "timeParticleEnum": 124,
          "tradeInflow": "11921883.540306628"
        },
        {
          "timeRange": "D2",
          "timeParticleEnum": 202,
          "tradeInflow": "16520581.362630488"
        },
        {
          "timeRange": "D3",
          "timeParticleEnum": 203,
          "tradeInflow": "24908715.907396115"
        },
        {
          "timeRange": "D5",
          "timeParticleEnum": 205,
          "tradeInflow": "19365986.345297877"
        },
        {
          "timeRange": "D7",
          "timeParticleEnum": 207,
          "tradeInflow": "-6748659.209922901"
        },
        {
          "timeRange": "D10",
          "timeParticleEnum": 210,
          "tradeInflow": "-38689591.78766655"
        },
        {
          "timeRange": "D15",
          "timeParticleEnum": 215,
          "tradeInflow": "-45520132.177442044"
        },
        {
          "timeRange": "D30",
          "timeParticleEnum": 230,
          "tradeInflow": "-81250761.75418144"
        },
        {
          "timeRange": "D40",
          "timeParticleEnum": 240,
          "tradeInflow": "-344003437.98125964"
        },
        {
          "timeRange": "D50",
          "timeParticleEnum": 250,
          "tradeInflow": "-395513703.7276248"
        },
        {
          "timeRange": "D60",
          "timeParticleEnum": 260,
          "tradeInflow": "-140844352.9521573"
        },
        {
          "timeRange": "D90",
          "timeParticleEnum": 290,
          "tradeInflow": "-456903413.74650776"
        },
        {
          "timeRange": "Y1",
          "timeParticleEnum": 401,
          "tradeInflow": "-2526756182.811581"
        },
        {
          "timeRange": "Y2",
          "timeParticleEnum": 402,
          "tradeInflow": "-5211174228.280086"
        },
        {
          "timeRange": "Y3",
          "timeParticleEnum": 403,
          "tradeInflow": "-6760377096.060281"
        },
        {
          "timeRange": "D120",
          "timeParticleEnum": 2120,
          "tradeInflow": "-363774991.1983446"
        },
        {
          "timeRange": "D150",
          "timeParticleEnum": 2150,
          "tradeInflow": "-419286657.2169454"
        },
        {
          "timeRange": "D180",
          "timeParticleEnum": 2180,
          "tradeInflow": "-564196691.8733132"
        }
      ]
    },
    {
      "updateTime": 1781713800000,
      "tradeType": 1,
      "tag": "HODLer",
      "tagsSimplified": "HODLer",
      "categoriesTradeDataList": [
        {
          "timeRange": "m5",
          "timeParticleEnum": 5,
          "tradeInflow": "57887.89060099999"
        },
        {
          "timeRange": "m15",
          "timeParticleEnum": 15,
          "tradeInflow": "24038.440862000036"
        },
        {
          "timeRange": "m30",
          "timeParticleEnum": 30,
          "tradeInflow": "33537.90474400014"
        },
        {
          "timeRange": "H1",
          "timeParticleEnum": 101,
          "tradeInflow": "203149.33309199972"
        },
        {
          "timeRange": "H2",
          "timeParticleEnum": 102,
          "tradeInflow": "-342659.72889300005"
        },
        {
          "timeRange": "H4",
          "timeParticleEnum": 104,
          "tradeInflow": "32602.34847299969"
        },
        {
          "timeRange": "H8",
          "timeParticleEnum": 108,
          "tradeInflow": "-137384.84313500044"
        },
        {
          "timeRange": "H12",
          "timeParticleEnum": 112,
          "tradeInflow": "435105.25445200014"
        },
        {
          "timeRange": "H24",
          "timeParticleEnum": 124,
          "tradeInflow": "570567.9564229988"
        },
        {
          "timeRange": "D2",
          "timeParticleEnum": 202,
          "tradeInflow": "-1606096.1178840012"
        },
        {
          "timeRange": "D3",
          "timeParticleEnum": 203,
          "tradeInflow": "-2962779.1250760006"
        },
        {
          "timeRange": "D5",
          "timeParticleEnum": 205,
          "tradeInflow": "-4383674.501961002"
        },
        {
          "timeRange": "D7",
          "timeParticleEnum": 207,
          "tradeInflow": "-24041993.633287005"
        },
        {
          "timeRange": "D10",
          "timeParticleEnum": 210,
          "tradeInflow": "-27183710.408040006"
        },
        {
          "timeRange": "D15",
          "timeParticleEnum": 215,
          "tradeInflow": "-34673909.228198014"
        },
        {
          "timeRange": "D30",
          "timeParticleEnum": 230,
          "tradeInflow": "-74997980.35413602"
        },
        {
          "timeRange": "D40",
          "timeParticleEnum": 240,
          "tradeInflow": "-108964870.39244603"
        },
        {
          "timeRange": "D50",
          "timeParticleEnum": 250,
          "tradeInflow": "-119750428.11536403"
        },
        {
          "timeRange": "D60",
          "timeParticleEnum": 260,
          "tradeInflow": "-126455075.65160103"
        },
        {
          "timeRange": "D90",
          "timeParticleEnum": 290,
          "tradeInflow": "-255045556.924052"
        },
        {
          "timeRange": "Y1",
          "timeParticleEnum": 401,
          "tradeInflow": "-102547925.52710001"
        },
        {
          "timeRange": "D120",
          "timeParticleEnum": 2120,
          "tradeInflow": "-311290101.84611595"
        },
        {
          "timeRange": "D150",
          "timeParticleEnum": 2150,
          "tradeInflow": "-477553073.289971"
        },
        {
          "timeRange": "D180",
          "timeParticleEnum": 2180,
          "tradeInflow": "-374584632.43463"
        }
      ]
    },
    {
      "updateTime": 1781713800000,
      "tradeType": 1,
      "tag": "Layer1_Layer2",
      "tagsSimplified": "一层/二层网络",
      "categoriesTradeDataList": [
        {
          "timeRange": "m5",
          "timeParticleEnum": 5,
          "tradeInflow": "5832677.060656184"
        },
        {
          "timeRange": "m15",
          "timeParticleEnum": 15,
          "tradeInflow": "4421468.295858057"
        },
        {
          "timeRange": "m30",
          "timeParticleEnum": 30,
          "tradeInflow": "5242498.564835228"
        },
        {
          "timeRange": "H1",
          "timeParticleEnum": 101,
          "tradeInflow": "13328015.444370415"
        },
        {
          "timeRange": "H2",
          "timeParticleEnum": 102,
          "tradeInflow": "6225750.937149532"
        },
        {
          "timeRange": "H4",
          "timeParticleEnum": 104,
          "tradeInflow": "-6244947.498242146"
        },
        {
          "timeRange": "H8",
          "timeParticleEnum": 108,
          "tradeInflow": "-35973694.38638514"
        },
        {
          "timeRange": "H12",
          "timeParticleEnum": 112,
          "tradeInflow": "-63633063.12849346"
        },
        {
          "timeRange": "H24",
          "timeParticleEnum": 124,
          "tradeInflow": "-45381747.62856409"
        },
        {
          "timeRange": "D2",
          "timeParticleEnum": 202,
          "tradeInflow": "-120879548.16797101"
        },
        {
          "timeRange": "D3",
          "timeParticleEnum": 203,
          "tradeInflow": "-58592438.044119105"
        },
        {
          "timeRange": "D5",
          "timeParticleEnum": 205,
          "tradeInflow": "-30376570.442840204"
        },
        {
          "timeRange": "D7",
          "timeParticleEnum": 207,
          "tradeInflow": "50258557.453116335"
        },
        {
          "timeRange": "D10",
          "timeParticleEnum": 210,
          "tradeInflow": "-23788096.106559645"
        },
        {
          "timeRange": "D15",
          "timeParticleEnum": 215,
          "tradeInflow": "-323449362.14701414"
        },
        {
          "timeRange": "D30",
          "timeParticleEnum": 230,
          "tradeInflow": "-632227697.7342763"
        },
        {
          "timeRange": "D40",
          "timeParticleEnum": 240,
          "tradeInflow": "-1231052261.5045385"
        },
        {
          "timeRange": "D50",
          "timeParticleEnum": 250,
          "tradeInflow": "-1721209943.682197"
        },
        {
          "timeRange": "D60",
          "timeParticleEnum": 260,
          "tradeInflow": "-1961799486.3802524"
        },
        {
          "timeRange": "D90",
          "timeParticleEnum": 290,
          "tradeInflow": "-2272785569.7483993"
        },
        {
          "timeRange": "Y1",
          "timeParticleEnum": 401,
          "tradeInflow": "-20710039521.044468"
        },
        {
          "timeRange": "Y2",
          "timeParticleEnum": 402,
          "tradeInflow": "-33810749108.2058"
        },
        {
          "timeRange": "Y3",
          "timeParticleEnum": 403,
          "tradeInflow": "-38095053480.657845"
        },
        {
          "timeRange": "D120",
          "timeParticleEnum": 2120,
          "tradeInflow": "-2427750365.0651603"
        },
        {
          "timeRange": "D150",
          "timeParticleEnum": 2150,
          "tradeInflow": "-5010338771.683902"
        },
        {
          "timeRange": "D180",
          "timeParticleEnum": 2180,
          "tradeInflow": "-4960619073.784833"
        }
      ]
    },
    {
      "updateTime": 1781713800000,
      "tradeType": 1,
      "tag": "mining-zone",
      "tagsSimplified": "mining-zone",
      "categoriesTradeDataList": [
        {
          "timeRange": "m5",
          "timeParticleEnum": 5,
          "tradeInflow": "11046017.2224704"
        },
        {
          "timeRange": "m15",
          "timeParticleEnum": 15,
          "tradeInflow": "8522845.067356419"
        },
        {
          "timeRange": "m30",
          "timeParticleEnum": 30,
          "tradeInflow": "2160846.0441146074"
        },
        {
          "timeRange": "H1",
          "timeParticleEnum": 101,
          "tradeInflow": "14614136.5332698"
        },
        {
          "timeRange": "H2",
          "timeParticleEnum": 102,
          "tradeInflow": "6304409.360924614"
        },
        {
          "timeRange": "H4",
          "timeParticleEnum": 104,
          "tradeInflow": "14097760.469367122"
        },
        {
          "timeRange": "H8",
          "timeParticleEnum": 108,
          "tradeInflow": "-17205377.875680707"
        },
        {
          "timeRange": "H12",
          "timeParticleEnum": 112,
          "tradeInflow": "-46926189.9586788"
        },
        {
          "timeRange": "H24",
          "timeParticleEnum": 124,
          "tradeInflow": "-19906341.469481837"
        },
        {
          "timeRange": "D2",
          "timeParticleEnum": 202,
          "tradeInflow": "-152347894.2954939"
        },
        {
          "timeRange": "D3",
          "timeParticleEnum": 203,
          "tradeInflow": "-72410871.70616284"
        },
        {
          "timeRange": "D5",
          "timeParticleEnum": 205,
          "tradeInflow": "-2671018.6531985924"
        },
        {
          "timeRange": "D7",
          "timeParticleEnum": 207,
          "tradeInflow": "150971356.20561552"
        },
        {
          "timeRange": "D10",
          "timeParticleEnum": 210,
          "tradeInflow": "73917163.63242936"
        },
        {
          "timeRange": "D15",
          "timeParticleEnum": 215,
          "tradeInflow": "-899219572.9429379"
        },
        {
          "timeRange": "D30",
          "timeParticleEnum": 230,
          "tradeInflow": "-1371779625.7999437"
        },
        {
          "timeRange": "D40",
          "timeParticleEnum": 240,
          "tradeInflow": "-2105416216.5219364"
        },
        {
          "timeRange": "D50",
          "timeParticleEnum": 250,
          "tradeInflow": "-2349798466.317535"
        },
        {
          "timeRange": "D60",
          "timeParticleEnum": 260,
          "tradeInflow": "-2636597824.983321"
        },
        {
          "timeRange": "D90",
          "timeParticleEnum": 290,
          "tradeInflow": "-2577529629.815121"
        },
        {
          "timeRange": "Y1",
          "timeParticleEnum": 401,
          "tradeInflow": "-41431239253.502426"
        },
        {
          "timeRange": "Y2",
          "timeParticleEnum": 402,
          "tradeInflow": "-69103299631.45773"
        },
        {
          "timeRange": "Y3",
          "timeParticleEnum": 403,
          "tradeInflow": "-77713799139.46542"
        },
        {
          "timeRange": "D120",
          "timeParticleEnum": 2120,
          "tradeInflow": "-3837637394.4623284"
        },
        {
          "timeRange": "D150",
          "timeParticleEnum": 2150,
          "tradeInflow": "-9864087538.615921"
        },
        {
          "timeRange": "D180",
          "timeParticleEnum": 2180,
          "tradeInflow": "-9524887829.217136"
        }
      ]
    },
    {
      "updateTime": 1781713800000,
      "tradeType": 1,
      "tag": "stablecoin",
      "tagsSimplified": "stablecoin",
      "categoriesTradeDataList": [
        {
          "timeRange": "m5",
          "timeParticleEnum": 5,
          "tradeInflow": "871764.0228100006"
        },
        {
          "timeRange": "m15",
          "timeParticleEnum": 15,
          "tradeInflow": "1680551.8737399997"
        },
        {
          "timeRange": "m30",
          "timeParticleEnum": 30,
          "tradeInflow": "2801307.967839999"
        },
        {
          "timeRange": "H1",
          "timeParticleEnum": 101,
          "tradeInflow": "-9138769.100449994"
        },
        {
          "timeRange": "H2",
          "timeParticleEnum": 102,
          "tradeInflow": "-26688855.463380005"
        },
        {
          "timeRange": "H4",
          "timeParticleEnum": 104,
          "tradeInflow": "-36139042.964250006"
        },
        {
          "timeRange": "H8",
          "timeParticleEnum": 108,
          "tradeInflow": "-70331437.33848001"
        },
        {
          "timeRange": "H12",
          "timeParticleEnum": 112,
          "tradeInflow": "-96719767.88250002"
        },
        {
          "timeRange": "H24",
          "timeParticleEnum": 124,
          "tradeInflow": "-185280546.72994998"
        },
        {
          "timeRange": "D2",
          "timeParticleEnum": 202,
          "tradeInflow": "-364263045.08950007"
        },
        {
          "timeRange": "D3",
          "timeParticleEnum": 203,
          "tradeInflow": "-635913879.5882599"
        },
        {
          "timeRange": "D5",
          "timeParticleEnum": 205,
          "tradeInflow": "-788784128.94335"
        },
        {
          "timeRange": "D7",
          "timeParticleEnum": 207,
          "tradeInflow": "-1286319234.3342903"
        },
        {
          "timeRange": "D10",
          "timeParticleEnum": 210,
          "tradeInflow": "-1677649255.41843"
        },
        {
          "timeRange": "D15",
          "timeParticleEnum": 215,
          "tradeInflow": "-2583302683.2782702"
        },
        {
          "timeRange": "D30",
          "timeParticleEnum": 230,
          "tradeInflow": "-4220479180.6202407"
        },
        {
          "timeRange": "D40",
          "timeParticleEnum": 240,
          "tradeInflow": "-4724782087.031189"
        },
        {
          "timeRange": "D50",
          "timeParticleEnum": 250,
          "tradeInflow": "-4845883862.70873"
        },
        {
          "timeRange": "D60",
          "timeParticleEnum": 260,
          "tradeInflow": "-4416607234.35151"
        },
        {
          "timeRange": "D90",
          "timeParticleEnum": 290,
          "tradeInflow": "-5082452693.124432"
        },
        {
          "timeRange": "Y1",
          "timeParticleEnum": 401,
          "tradeInflow": "-12231752977.782871"
        },
        {
          "timeRange": "Y2",
          "timeParticleEnum": 402,
          "tradeInflow": "-15852084915.822195"
        },
        {
          "timeRange": "Y3",
          "timeParticleEnum": 403,
          "tradeInflow": "-21024486696.643745"
        },
        {
          "timeRange": "D120",
          "timeParticleEnum": 2120,
          "tradeInflow": "-6092461781.31015"
        },
        {
          "timeRange": "D150",
          "timeParticleEnum": 2150,
          "tradeInflow": "-6763041278.04893"
        },
        {
          "timeRange": "D180",
          "timeParticleEnum": 2180,
          "tradeInflow": "-7156204709.155908"
        }
      ]
    },
    {
      "updateTime": 1781713800000,
      "tradeType": 1,
      "tag": "Meme",
      "tagsSimplified": "Meme",
      "categoriesTradeDataList": [
        {
          "timeRange": "m5",
          "timeParticleEnum": 5,
          "tradeInflow": "291110.91178908997"
        },
        {
          "timeRange": "m15",
          "timeParticleEnum": 15,
          "tradeInflow": "480173.11041394004"
        },
        {
          "timeRange": "m30",
          "timeParticleEnum": 30,
          "tradeInflow": "259498.89778052998"
        },
        {
          "timeRange": "H1",
          "timeParticleEnum": 101,
          "tradeInflow": "398758.81534668995"
        },
        {
          "timeRange": "H2",
          "timeParticleEnum": 102,
          "tradeInflow": "5870.781514400055"
        },
        {
          "timeRange": "H4",
          "timeParticleEnum": 104,
          "tradeInflow": "-731868.0319579798"
        },
        {
          "timeRange": "H8",
          "timeParticleEnum": 108,
          "tradeInflow": "-3420177.0022118"
        },
        {
          "timeRange": "H12",
          "timeParticleEnum": 112,
          "tradeInflow": "-3559034.488636968"
        },
        {
          "timeRange": "H24",
          "timeParticleEnum": 124,
          "tradeInflow": "-3638930.6418003757"
        },
        {
          "timeRange": "D2",
          "timeParticleEnum": 202,
          "tradeInflow": "-8949068.373591414"
        },
        {
          "timeRange": "D3",
          "timeParticleEnum": 203,
          "tradeInflow": "-8072588.943708688"
        },
        {
          "timeRange": "D5",
          "timeParticleEnum": 205,
          "tradeInflow": "-10351112.154791413"
        },
        {
          "timeRange": "D7",
          "timeParticleEnum": 207,
          "tradeInflow": "-6466770.856709796"
        },
        {
          "timeRange": "D10",
          "timeParticleEnum": 210,
          "tradeInflow": "-13989754.228119487"
        },
        {
          "timeRange": "D15",
          "timeParticleEnum": 215,
          "tradeInflow": "-31862248.01759645"
        },
        {
          "timeRange": "D30",
          "timeParticleEnum": 230,
          "tradeInflow": "-104298399.81808375"
        },
        {
          "timeRange": "D40",
          "timeParticleEnum": 240,
          "tradeInflow": "-84977034.2245339"
        },
        {
          "timeRange": "D50",
          "timeParticleEnum": 250,
          "tradeInflow": "-84095699.36268485"
        },
        {
          "timeRange": "D60",
          "timeParticleEnum": 260,
          "tradeInflow": "-64022741.31015475"
        },
        {
          "timeRange": "D90",
          "timeParticleEnum": 290,
          "tradeInflow": "-125069275.10583055"
        },
        {
          "timeRange": "Y1",
          "timeParticleEnum": 401,
          "tradeInflow": "-3339507719.8672705"
        },
        {
          "timeRange": "Y2",
          "timeParticleEnum": 402,
          "tradeInflow": "-8091439746.623852"
        },
        {
          "timeRange": "Y3",
          "timeParticleEnum": 403,
          "tradeInflow": "-6629173508.276914"
        },
        {
          "timeRange": "D120",
          "timeParticleEnum": 2120,
          "tradeInflow": "-245571048.89533222"
        },
        {
          "timeRange": "D150",
          "timeParticleEnum": 2150,
          "tradeInflow": "-407974793.165709"
        },
        {
          "timeRange": "D180",
          "timeParticleEnum": 2180,
          "tradeInflow": "-606225229.7510293"
        }
      ]
    },
    {
      "updateTime": 1781713800000,
      "tradeType": 1,
      "tag": "Seed",
      "tagsSimplified": "种子",
      "categoriesTradeDataList": [
        {
          "timeRange": "m5",
          "timeParticleEnum": 5,
          "tradeInflow": "614789.5587504503"
        },
        {
          "timeRange": "m15",
          "timeParticleEnum": 15,
          "tradeInflow": "672526.8641143802"
        },
        {
          "timeRange": "m30",
          "timeParticleEnum": 30,
          "tradeInflow": "1486361.2708546694"
        },
        {
          "timeRange": "H1",
          "timeParticleEnum": 101,
          "tradeInflow": "1244224.434679319"
        },
        {
          "timeRange": "H2",
          "timeParticleEnum": 102,
          "tradeInflow": "1904646.9910800692"
        },
        {
          "timeRange": "H4",
          "timeParticleEnum": 104,
          "tradeInflow": "-2270459.2316504973"
        },
        {
          "timeRange": "H8",
          "timeParticleEnum": 108,
          "tradeInflow": "-8671434.048079684"
        },
        {
          "timeRange": "H12",
          "timeParticleEnum": 112,
          "tradeInflow": "-13962813.155269427"
        },
        {
          "timeRange": "H24",
          "timeParticleEnum": 124,
          "tradeInflow": "-13892421.457140604"
        },
        {
          "timeRange": "D2",
          "timeParticleEnum": 202,
          "tradeInflow": "-31340569.677887294"
        },
        {
          "timeRange": "D3",
          "timeParticleEnum": 203,
          "tradeInflow": "-33464845.905257553"
        },
        {
          "timeRange": "D5",
          "timeParticleEnum": 205,
          "tradeInflow": "-41153239.603789836"
        },
        {
          "timeRange": "D7",
          "timeParticleEnum": 207,
          "tradeInflow": "-67746750.54860894"
        },
        {
          "timeRange": "D10",
          "timeParticleEnum": 210,
          "tradeInflow": "-102520686.59265584"
        },
        {
          "timeRange": "D15",
          "timeParticleEnum": 215,
          "tradeInflow": "-135622922.35218778"
        },
        {
          "timeRange": "D30",
          "timeParticleEnum": 230,
          "tradeInflow": "-213100966.10263735"
        },
        {
          "timeRange": "D40",
          "timeParticleEnum": 240,
          "tradeInflow": "-489453743.1342265"
        },
        {
          "timeRange": "D50",
          "timeParticleEnum": 250,
          "tradeInflow": "-599210222.1696237"
        },
        {
          "timeRange": "D60",
          "timeParticleEnum": 260,
          "tradeInflow": "-364141222.2065424"
        },
        {
          "timeRange": "D90",
          "timeParticleEnum": 290,
          "tradeInflow": "-964176222.1467202"
        },
        {
          "timeRange": "Y1",
          "timeParticleEnum": 401,
          "tradeInflow": "-1667720052.714189"
        },
        {
          "timeRange": "Y2",
          "timeParticleEnum": 402,
          "tradeInflow": "-3836920841.7715716"
        },
        {
          "timeRange": "Y3",
          "timeParticleEnum": 403,
          "tradeInflow": "-1256824940.4553828"
        },
        {
          "timeRange": "D120",
          "timeParticleEnum": 2120,
          "tradeInflow": "-656585458.2855276"
        },
        {
          "timeRange": "D150",
          "timeParticleEnum": 2150,
          "tradeInflow": "-1107650404.7147644"
        },
        {
          "timeRange": "D180",
          "timeParticleEnum": 2180,
          "tradeInflow": "-878556464.1089923"
        }
      ]
    },
    {
      "updateTime": 1781713800000,
      "tradeType": 1,
      "tag": "fan_token",
      "tagsSimplified": "粉丝代币",
      "categoriesTradeDataList": [
        {
          "timeRange": "m5",
          "timeParticleEnum": 5,
          "tradeInflow": "9040.184619999998"
        },
        {
          "timeRange": "m15",
          "timeParticleEnum": 15,
          "tradeInflow": "23924.576249999995"
        },
        {
          "timeRange": "m30",
          "timeParticleEnum": 30,
          "tradeInflow": "28983.089179999995"
        },
        {
          "timeRange": "H1",
          "timeParticleEnum": 101,
          "tradeInflow": "43857.78387000001"
        },
        {
          "timeRange": "H2",
          "timeParticleEnum": 102,
          "tradeInflow": "89120.15969000006"
        },
        {
          "timeRange": "H4",
          "timeParticleEnum": 104,
          "tradeInflow": "81365.08950000007"
        },
        {
          "timeRange": "H8",
          "timeParticleEnum": 108,
          "tradeInflow": "1725.6998000000906"
        },
        {
          "timeRange": "H12",
          "timeParticleEnum": 112,
          "tradeInflow": "378769.86818000034"
        },
        {
          "timeRange": "H24",
          "timeParticleEnum": 124,
          "tradeInflow": "462328.0689700004"
        },
        {
          "timeRange": "D2",
          "timeParticleEnum": 202,
          "tradeInflow": "774181.1379100005"
        },
        {
          "timeRange": "D3",
          "timeParticleEnum": 203,
          "tradeInflow": "251211.59129000021"
        },
        {
          "timeRange": "D5",
          "timeParticleEnum": 205,
          "tradeInflow": "42627.827220000705"
        },
        {
          "timeRange": "D7",
          "timeParticleEnum": 207,
          "tradeInflow": "-766162.6345799993"
        },
        {
          "timeRange": "D10",
          "timeParticleEnum": 210,
          "tradeInflow": "-2789393.4799999995"
        },
        {
          "timeRange": "D15",
          "timeParticleEnum": 215,
          "tradeInflow": "-5361888.67081"
        },
        {
          "timeRange": "D30",
          "timeParticleEnum": 230,
          "tradeInflow": "-15491031.173619997"
        },
        {
          "timeRange": "D40",
          "timeParticleEnum": 240,
          "tradeInflow": "-18016446.923639998"
        },
        {
          "timeRange": "D50",
          "timeParticleEnum": 250,
          "tradeInflow": "-20952254.859359995"
        },
        {
          "timeRange": "D60",
          "timeParticleEnum": 260,
          "tradeInflow": "-24778298.248139996"
        },
        {
          "timeRange": "D90",
          "timeParticleEnum": 290,
          "tradeInflow": "-27920972.57499"
        },
        {
          "timeRange": "Y1",
          "timeParticleEnum": 401,
          "tradeInflow": "-124462672.80884899"
        },
        {
          "timeRange": "Y2",
          "timeParticleEnum": 402,
          "tradeInflow": "-257587253.81143597"
        },
        {
          "timeRange": "Y3",
          "timeParticleEnum": 403,
          "tradeInflow": "-601833061.0471547"
        },
        {
          "timeRange": "D120",
          "timeParticleEnum": 2120,
          "tradeInflow": "-31554544.29368"
        },
        {
          "timeRange": "D150",
          "timeParticleEnum": 2150,
          "tradeInflow": "-36547280.48499"
        },
        {
          "timeRange": "D180",
          "timeParticleEnum": 2180,
          "tradeInflow": "-59997579.79549"
        }
      ]
    },
    {
      "updateTime": 1781713800000,
      "tradeType": 1,
      "tag": "Gaming",
      "tagsSimplified": "游戏",
      "categoriesTradeDataList": [
        {
          "timeRange": "m5",
          "timeParticleEnum": 5,
          "tradeInflow": "14850.47106162"
        },
        {
          "timeRange": "m15",
          "timeParticleEnum": 15,
          "tradeInflow": "23020.510284009993"
        },
        {
          "timeRange": "m30",
          "timeParticleEnum": 30,
          "tradeInflow": "3979.1811368799936"
        },
        {
          "timeRange": "H1",
          "timeParticleEnum": 101,
          "tradeInflow": "779.0659553600318"
        },
        {
          "timeRange": "H2",
          "timeParticleEnum": 102,
          "tradeInflow": "-47926.02711898"
        },
        {
          "timeRange": "H4",
          "timeParticleEnum": 104,
          "tradeInflow": "-109497.27537547005"
        },
        {
          "timeRange": "H8",
          "timeParticleEnum": 108,
          "tradeInflow": "-490775.72191374016"
        },
        {
          "timeRange": "H12",
          "timeParticleEnum": 112,
          "tradeInflow": "-744815.8887458103"
        },
        {
          "timeRange": "H24",
          "timeParticleEnum": 124,
          "tradeInflow": "-1043025.7173414902"
        },
        {
          "timeRange": "D2",
          "timeParticleEnum": 202,
          "tradeInflow": "-1085958.0695761908"
        },
        {
          "timeRange": "D3",
          "timeParticleEnum": 203,
          "tradeInflow": "-1297757.8561886805"
        },
        {
          "timeRange": "D5",
          "timeParticleEnum": 205,
          "tradeInflow": "-3094651.294650441"
        },
        {
          "timeRange": "D7",
          "timeParticleEnum": 207,
          "tradeInflow": "-4250845.3466661805"
        },
        {
          "timeRange": "D10",
          "timeParticleEnum": 210,
          "tradeInflow": "-5448832.371937741"
        },
        {
          "timeRange": "D15",
          "timeParticleEnum": 215,
          "tradeInflow": "-6421066.0591986505"
        },
        {
          "timeRange": "D30",
          "timeParticleEnum": 230,
          "tradeInflow": "-7408080.5659205355"
        },
        {
          "timeRange": "D40",
          "timeParticleEnum": 240,
          "tradeInflow": "-24364647.70954669"
        },
        {
          "timeRange": "D50",
          "timeParticleEnum": 250,
          "tradeInflow": "-39955638.429765195"
        },
        {
          "timeRange": "D60",
          "timeParticleEnum": 260,
          "tradeInflow": "-46948213.86252669"
        },
        {
          "timeRange": "D90",
          "timeParticleEnum": 290,
          "tradeInflow": "-26133094.400064193"
        },
        {
          "timeRange": "Y1",
          "timeParticleEnum": 401,
          "tradeInflow": "-274148673.6877174"
        },
        {
          "timeRange": "Y2",
          "timeParticleEnum": 402,
          "tradeInflow": "-1275917456.0850015"
        },
        {
          "timeRange": "Y3",
          "timeParticleEnum": 403,
          "tradeInflow": "-1169525703.81334"
        },
        {
          "timeRange": "D120",
          "timeParticleEnum": 2120,
          "tradeInflow": "-12920011.120923646"
        },
        {
          "timeRange": "D150",
          "timeParticleEnum": 2150,
          "tradeInflow": "-26116737.473680064"
        },
        {
          "timeRange": "D180",
          "timeParticleEnum": 2180,
          "tradeInflow": "-28553095.334619015"
        }
      ]
    },
    {
      "updateTime": 1781713800000,
      "tradeType": 1,
      "tag": "storage-zone",
      "tagsSimplified": "存储",
      "categoriesTradeDataList": [
        {
          "timeRange": "m5",
          "timeParticleEnum": 5,
          "tradeInflow": "488877.5635277098"
        },
        {
          "timeRange": "m15",
          "timeParticleEnum": 15,
          "tradeInflow": "416093.9803918199"
        },
        {
          "timeRange": "m30",
          "timeParticleEnum": 30,
          "tradeInflow": "429339.74590499996"
        },
        {
          "timeRange": "H1",
          "timeParticleEnum": 101,
          "tradeInflow": "608133.3650040599"
        },
        {
          "timeRange": "H2",
          "timeParticleEnum": 102,
          "tradeInflow": "604530.1795427601"
        },
        {
          "timeRange": "H4",
          "timeParticleEnum": 104,
          "tradeInflow": "645636.09351245"
        },
        {
          "timeRange": "H8",
          "timeParticleEnum": 108,
          "tradeInflow": "929423.5732987602"
        },
        {
          "timeRange": "H12",
          "timeParticleEnum": 112,
          "tradeInflow": "1157853.41636981"
        },
        {
          "timeRange": "H24",
          "timeParticleEnum": 124,
          "tradeInflow": "1468985.8151027204"
        },
        {
          "timeRange": "D2",
          "timeParticleEnum": 202,
          "tradeInflow": "1122863.8917557101"
        },
        {
          "timeRange": "D3",
          "timeParticleEnum": 203,
          "tradeInflow": "1640852.3818730002"
        },
        {
          "timeRange": "D5",
          "timeParticleEnum": 205,
          "tradeInflow": "1831886.8519642004"
        },
        {
          "timeRange": "D7",
          "timeParticleEnum": 207,
          "tradeInflow": "1610231.1390772006"
        },
        {
          "timeRange": "D10",
          "timeParticleEnum": 210,
          "tradeInflow": "1633862.4328538005"
        },
        {
          "timeRange": "D15",
          "timeParticleEnum": 215,
          "tradeInflow": "-1770884.3290993108"
        },
        {
          "timeRange": "D30",
          "timeParticleEnum": 230,
          "tradeInflow": "-9773145.86563833"
        },
        {
          "timeRange": "D40",
          "timeParticleEnum": 240,
          "tradeInflow": "-15942035.023418942"
        },
        {
          "timeRange": "D50",
          "timeParticleEnum": 250,
          "tradeInflow": "-11586828.039975708"
        },
        {
          "timeRange": "D60",
          "timeParticleEnum": 260,
          "tradeInflow": "-15620475.632764969"
        },
        {
          "timeRange": "D90",
          "timeParticleEnum": 290,
          "tradeInflow": "-13460557.34003894"
        },
        {
          "timeRange": "Y1",
          "timeParticleEnum": 401,
          "tradeInflow": "-275611845.5357347"
        },
        {
          "timeRange": "Y2",
          "timeParticleEnum": 402,
          "tradeInflow": "-875673903.7669094"
        },
        {
          "timeRange": "Y3",
          "timeParticleEnum": 403,
          "tradeInflow": "-1575400201.358917"
        },
        {
          "timeRange": "D120",
          "timeParticleEnum": 2120,
          "tradeInflow": "-19604712.765082795"
        },
        {
          "timeRange": "D150",
          "timeParticleEnum": 2150,
          "tradeInflow": "-34898293.12703091"
        },
        {
          "timeRange": "D180",
          "timeParticleEnum": 2180,
          "tradeInflow": "-56393366.27190279"
        }
      ]
    }
  ],
  "snapshot": {
    "name": "sector_fund",
    "saved_at": "2026-06-17T16:33:30.562235+00:00",
    "origin": "live",
    "history_id": "2026-06-17T16-33-30.562235+00-00",
    "history_path": "D:\\work\\gitee\\web3-quant-sandbox\\data\\dashboard\\snapshots\\history\\sector_fund\\2026-06-17T16-33-30.562235+00-00.json"
  }
}